{"Date":"2021-04-13","Code":"39000D30160I","CodeHuman":"D3013","From":"汉口","To":"上海虹桥","Path":[{"StationName":"汉口","ArrivalTime":0,"DepartureTime":1618300800},{"StationName":"红安西","ArrivalTime":1618302540,"DepartureTime":1618302660},{"StationName":"麻城北","ArrivalTime":1618303440,"DepartureTime":1618303560},{"StationName":"金寨","ArrivalTime":1618305480,"DepartureTime":1618305600},{"StationName":"合肥南","ArrivalTime":1618308120,"DepartureTime":1618308480},{"StationName":"全椒","ArrivalTime":1618310340,"DepartureTime":1618310460},{"StationName":"南京南","ArrivalTime":1618311720,"DepartureTime":1618311840},{"StationName":"镇江","ArrivalTime":1618313520,"DepartureTime":1618314120},{"StationName":"常州","ArrivalTime":1618315620,"DepartureTime":1618315740},{"StationName":"无锡","ArrivalTime":1618316640,"DepartureTime":1618316760},{"StationName":"苏州","ArrivalTime":1618317660,"DepartureTime":1618317840},{"StationName":"昆山南","ArrivalTime":1618318560,"DepartureTime":1618318680},{"StationName":"上海虹桥","ArrivalTime":1618319880,"DepartureTime":0}]}