{"Date":"2021-04-13","Code":"5l000D3032E0","CodeHuman":"D3033","From":"上海虹桥","To":"汉口","Path":[{"StationName":"上海虹桥","ArrivalTime":0,"DepartureTime":1618326960},{"StationName":"昆山南","ArrivalTime":1618328100,"DepartureTime":1618328220},{"StationName":"苏州","ArrivalTime":1618329000,"DepartureTime":1618329120},{"StationName":"无锡","ArrivalTime":1618330020,"DepartureTime":1618330140},{"StationName":"镇江","ArrivalTime":1618332300,"DepartureTime":1618332600},{"StationName":"南京南","ArrivalTime":1618334340,"DepartureTime":1618334700},{"StationName":"肥东","ArrivalTime":1618337100,"DepartureTime":1618337220},{"StationName":"合肥南","ArrivalTime":1618337940,"DepartureTime":1618338180},{"StationName":"六安","ArrivalTime":1618339860,"DepartureTime":1618340100},{"StationName":"麻城北","ArrivalTime":1618342860,"DepartureTime":1618343700},{"StationName":"汉口","ArrivalTime":1618346160,"DepartureTime":0}]}