{"Date":"2021-04-13","Code":"5l000G177241","CodeHuman":"G1773","From":"上海虹桥","To":"长沙南","Path":[{"StationName":"上海虹桥","ArrivalTime":0,"DepartureTime":1618296420},{"StationName":"苏州北","ArrivalTime":1618297800,"DepartureTime":1618297920},{"StationName":"常州北","ArrivalTime":1618299240,"DepartureTime":1618299360},{"StationName":"丹阳北","ArrivalTime":1618300080,"DepartureTime":1618300380},{"StationName":"镇江南","ArrivalTime":1618301040,"DepartureTime":1618301340},{"StationName":"南京南","ArrivalTime":1618302540,"DepartureTime":1618302660},{"StationName":"合肥南","ArrivalTime":1618305540,"DepartureTime":1618305780},{"StationName":"金寨","ArrivalTime":1618308240,"DepartureTime":1618308360},{"StationName":"武汉","ArrivalTime":1618312080,"DepartureTime":1618312680},{"StationName":"咸宁北","ArrivalTime":1618314120,"DepartureTime":1618314240},{"StationName":"岳阳东","ArrivalTime":1618316040,"DepartureTime":1618316160},{"StationName":"长沙南","ArrivalTime":1618318200,"DepartureTime":0}]}