{"Date":"2021-04-13","Code":"77000G19760C","CodeHuman":"G1973","From":"重庆西","To":"上海虹桥","Path":[{"StationName":"重庆西","ArrivalTime":0,"DepartureTime":1618305300},{"StationName":"内江北","ArrivalTime":1618307880,"DepartureTime":1618308120},{"StationName":"成都东","ArrivalTime":1618310760,"DepartureTime":1618311360},{"StationName":"德阳","ArrivalTime":1618312800,"DepartureTime":1618312920},{"StationName":"绵阳","ArrivalTime":1618313940,"DepartureTime":1618314060},{"StationName":"江油","ArrivalTime":1618315080,"DepartureTime":1618315200},{"StationName":"广元","ArrivalTime":1618317600,"DepartureTime":1618317960},{"StationName":"宁强南","ArrivalTime":1618319280,"DepartureTime":1618319400},{"StationName":"汉中","ArrivalTime":1618320900,"DepartureTime":1618321260},{"StationName":"佛坪","ArrivalTime":1618323060,"DepartureTime":1618323180},{"StationName":"西安北","ArrivalTime":1618326060,"DepartureTime":1618326900},{"StationName":"华山北","ArrivalTime":1618328580,"DepartureTime":1618328700},{"StationName":"洛阳龙门","ArrivalTime":1618331820,"DepartureTime":1618331940},{"StationName":"郑州东","ArrivalTime":1618334220,"DepartureTime":1618334400},{"StationName":"商丘","ArrivalTime":1618337400,"DepartureTime":1618337880},{"StationName":"萧县北","ArrivalTime":1618339740,"DepartureTime":1618339920},{"StationName":"徐州东","ArrivalTime":1618341060,"DepartureTime":1618341600},{"StationName":"宿州东","ArrivalTime":1618342740,"DepartureTime":1618342860},{"StationName":"蚌埠南","ArrivalTime":1618344240,"DepartureTime":1618344780},{"StationName":"南京南","ArrivalTime":1618347300,"DepartureTime":1618347420},{"StationName":"镇江南","ArrivalTime":1618348560,"DepartureTime":1618348680},{"StationName":"无锡东","ArrivalTime":1618350480,"DepartureTime":1618350600},{"StationName":"苏州北","ArrivalTime":1618351200,"DepartureTime":1618351320},{"StationName":"上海虹桥","ArrivalTime":1618352700,"DepartureTime":0}]}