{"Date":"2021-04-13","Code":"5l000G7156E0","CodeHuman":"G7157","From":"上海虹桥","To":"合肥南","Path":[{"StationName":"上海虹桥","ArrivalTime":0,"DepartureTime":1618338360},{"StationName":"昆山南","ArrivalTime":1618339500,"DepartureTime":1618339620},{"StationName":"苏州","ArrivalTime":1618340280,"DepartureTime":1618340400},{"StationName":"无锡","ArrivalTime":1618341300,"DepartureTime":1618341420},{"StationName":"惠山","ArrivalTime":1618341960,"DepartureTime":1618342380},{"StationName":"常州","ArrivalTime":1618343040,"DepartureTime":1618343160},{"StationName":"丹阳","ArrivalTime":1618344120,"DepartureTime":1618344420},{"StationName":"镇江","ArrivalTime":1618345140,"DepartureTime":1618345260},{"StationName":"南京南","ArrivalTime":1618346940,"DepartureTime":1618347180},{"StationName":"合肥南","ArrivalTime":1618350060,"DepartureTime":0}]}